Workbook

Sheet DRA. ALEJANDRA
A6: DRA. ALEJANDRA
A7: FECHA | B7: NOMBRE DEL PACIENTE | C7: TIPO DE CONSULTA | D7: MONTO | E7: MEDIO DE PAGO | F7: FACTURADO | G7: NÚMERO RECIBO | H7: NÚMERO FACTURA | I7: FUENTE | J7: OBSERVACIONES | K7: Columna1
A8: 46144 | B8: Julio Aguilar | C8: transplante | D8: 100000 | E8: TARJETA CREDITO | F8: si
A9: 46146 | B9: Paola Huelga Correa | C9: subsecuetne | D9: 1800 | E9: AMEX | F9: no | J9: se cobro dr.Barrera 7/5/26
A10: 46146 | B10: Paola Huelga Correa | C10: AG gel + 1 vastionin | D10: 1500 | E10: AMEX | F10: no | J10: se cobro dr.Barrera
A11: 46146 | B11: Esteban Campos Valladolid | C11: procedimiento | D11: 2500 | E11: TARJETA CREDITO | F11: si
A12: 46146 | B12: KARLO IMANUEL GALINDO RAMIREZ | C12: Subsecuente | D12: 1800 | E12: TARJETA CREDITO | F12: NO
A13: 46146 | B13: Cecilia Valladolid | C13: Subsecuente | D13: 1800 | E13: TARJETA CREDITO | F13: si
A14: 46146 | B14: Marco Antonio Torres Pérez | C14: Subsecuente | D14: 0 | E14: CORTESÍA
A15: 46146 | B15: Rebeca Kababie | C15: Procedimiento | D15: 3500 | E15: TARJETA CREDITO | F15: no
A16: 46146 | B16: Fernando Terres | C16: CO2 | D16: 3000 | E16: TARJETA CREDITO
A17: 46146 | B17: Fernando Terres | C17: shampoo | D17: 1200 | E17: TARJETA CREDITO
A18: 46147 | B18: Cecilia Ramírez Suttclife | C18: subsecuente | D18: 1800 | E18: AMEX | F18: si
A19: 46147 | B19: Cecilia Ramírez Suttclife | C19: 1 minoxidil | D19: 2500 | E19: AMEX | F19: si
A20: 46147 | B20: Cecilia Ramírez Suttclife | C20: liauronidaza | D20: 3000 | E20: AMEX | F20: si
A21: 46147 | B21: Cecilia Ramírez Suttclife | C21: tizo 3 | D21: 1200 | E21: AMEX | F21: si
A22: 46147 | B22: Moshe Chocron Benabou | C22: PV | D22: 1640 | E22: TARJETA CREDITO | F22: no | J22: tenia s/f 29/04/
A23: 46147 | B23: Claudia Maribel Pérez Hernandez | C23: botox | D23: 6500 | E23: visa | F23: no
A24: 46147 | B24: Javier sayrols Bouigue | C24: PV | D24: 1800 | E24: EFECTIVO | F24: no | J24: Saldo a favor$200
A25: 46147 | B25: Gustavo Adolfo Espinosa Carbajal | C25: subsecuente | D25: 0 | E25: CORTESÍA
A26: 46147 | B26: Laura Duhart Gutiérrez | C26: CD dermico loción capilar | D26: 800 | E26: TRANSFERENCIA | F26: no
A27: 46148 | B27: Tamara Beatriz Muñoz Delgadillo | C27: consulta | D27: 1800 | E27: TARJETA CREDITO | F27: si
A28: 46148 | B28: Tamara Beatriz Muñoz Delgadillo | C28: skin glow | D28: 1300 | E28: TARJETA CREDITO | F28: si
A29: 46148 | B29: Tamara Beatriz Muñoz Delgadillo | C29: solución | D29: 500 | E29: TARJETA CREDITO | F29: si | J29: pend, entregar sol.
A30: 46148 | B30: Soylo Montes de Oca Olguín | C30: subsecuente | D30: 1800 | E30: TARJETA CREDITO | F30: si
A31: 46148 | B31: Mariana Evelyn Carrillo González | C31: botox | D31: 5850 | E31: EFECTIVO
A32: 46148 | B32: Mariana Evelyn Carrillo González | C32: vastionin | D32: 1000 | E32: EFECTIVO
A33: 46148 | B33: Kiyomi Alvarado Tanamachi | C33: subsecuente | D33: 1800 | E33: TARJETA CREDITO | F33: no
A34: 46148 | B34: Zeltzin Rosas Espinoza | C34: retoque | D34: 0 | E34: CORTESÍA
A35: 46148 | B35: Ledicia Benabou Benmaman | C35: subsecuente | D35: 1800 | E35: EFECTIVO | F35: no
A36: 46148 | B36: Araceli Plaza Vázquez | C36: acido hiauloronico/radiesse | D36: 21250 | E36: TARJETA CREDITO | F36: no
A37: 46148 | B37: Miguel Angel Tejeda Calvario | C37: ssubsecuente | D37: 0 | E37: CORTESÍA
A38: 46148 | B38: Diana Neri Neri | C38: PV/BOTOX | D38: 5525 | E38: TARJETA CREDITO | F38: si
A39: 46148 | B39: Carlos Figueroa Cobos | C39: BOTOX | D39: 5525 | E39: TARJETA CREDITO | F39: si
A40: 46148 | B40: Ximena Gomez Leites | C40: PV | D40: 1800 | E40: TARJETA CREDITO | F40: no
A41: 46148 | B41: Ximena Gomez Leites | C41: pastillas | D41: 1000 | E41: TARJETA CREDITO | F41: no
A42: 46148 | B42: Grecia Moreno | C42: botox | D42: 3500 | E42: TARJETA CREDITO | F42: no
A43: 46148 | B43: Grecia Moreno | C43: pastillas | D43: 1000 | E43: TARJETA CREDITO | F43: no
A44: 46149 | B44: Diana Morgado Iglesias | C44: 1 minoxidil 1 mg | D44: 2500 | E44: TARJETA CREDITO | F44: no | J44: se cobro dr.Barrera
A45: 46149 | B45: Paola Huelga Correa | C45: Subsecuente | D45: 1800 | E45: AMEX | F45: no | J45: pago Pen. 04/07 | K45: se cobro dr.Barrera 7/5/26
A46: 46149 | B46: Paola Huelga Correa | C46: AG gel + 1 vastionin | D46: 1500 | E46: AMEX | F46: no
A47: 46150 | B47: Federico Cedillo | C47: PV | D47: 1800 | E47: TARJETA CREDITO | F47: si
A48: 46150 | B48: Kleide Fernández Alvarez | C48: subsecuente | D48: 1800 | E48: TARJETA CREDITO | F48: si
A49: 46150 | B49: Marcela Soto | C49: subsecuente | D49: 1800 | E49: TARJETA DEBITO | F49: si
A50: 46150 | B50: Marcela Soto | C50: 1 minoxidil | D50: 2500 | E50: TARJETA DEBITO | F50: si
A51: 46150 | B51: Judith Escobar Torres | C51: retiro de puntos | D51: 0 | E51: CORTESÍA
A52: 46150 | B52: Maria Eugenia Ballestero Cameroni | C52: PV/procedimiento | D52: 2000 | E52: EFECTIVO | F52: no
A53: 46150 | B53: Maria Eugenia Ballestero Cameroni | C53: procedimeinto | D53: 4000 | E53: TARJETA CREDITO | F53: no
A54: 46150 | B54: Rodrigo Zarate Gonzalez | C54: procedimiento | D54: 2500 | E54: TARJETA CREDITO | F54: si
A55: 46150 | B55: Camila Soto | C55: subsecuente | D55: 1800 | E55: TARJETA DEBITO | F55: no
A56: 46150 | B56: Camila Soto | C56: AG GEL | D56: 500 | E56: TARJETA DEBITO | F56: no
A57: 46150 | B57: Camila Soto | C57: ACIDO TRANEXAMICO | D57: 1000 | E57: TARJETA DEBITO | J57: medicamento dr.
A58: 46150 | B58: Silvana Fajardo Bahena | C58: subsecuente | D58: 1800 | E58: TARJETA CREDITO | F58: si
A59: 46150 | B59: Ricardo Rivas García | C59: PV/consulta en línea
A60: 46150 | B60: Hannia Liz Palencia Paniagua | C60: subsecuente | D60: 1800 | E60: TARJETA CREDITO | F60: no
A61: 46150 | B61: Horacio Palencia Cisneros | C61: subsecuente | D61: 1800 | E61: TARJETA CREDITO | F61: no
A62: 46150 | B62: Abigail Paniagua Vizcarra | C62: subsecuente | D62: 1800 | E62: TARJETA CREDITO | F62: no
A63: 46150 | B63: Ingrid Pérez Tejeda | C63: subsecuente/LASER | D63: 3300 | E63: TARJETA CREDITO | F63: NO
A64: 46150 | B64: Dulce Sabrina Tello Martínez | C64: PV | D64: 1800 | E64: TARJETA CREDITO | F64: SI
A65: 46150 | B65: Adolfo Garin | C65: subsecuente | D65: 3500 | E65: TARJETA CREDITO | F65: si
A66: 46150 | B66: Maria Elena Aniceto | C66: 2 vastionin | D66: 2000 | E66: EFECTIVO | F66: no
A67: 46151 | B67: Victor Manuel Silva | C67: 1 minoxidil 5mg | D67: 2500 | E67: TARJETA CREDITO | F67: no | J67: se cobro dr. Barrera
A68: 46153 | B68: Roxana Vazquez Martinez | C68: subsecuente | D68: 0 | E68: CORTESÍA
A69: 46153 | B69: Sandra Eliana Garcia | C69: retoque | D69: 0 | E69: CORTESÍA
A70: 46153 | B70: Paulo Benziger Chávez | C70: subsecuente | D70: 0 | E70: CORTESÍA
A71: 46153 | B71: Ines Villegas | C71: PV Consulta en línea | D71: 1800 | E71: TRANSFERENCIA
A72: 46153 | B72: Denise Salas | C72: subsecuente | D72: 1800 | E72: TARJETA DEBITO | F72: no
A73: 46153 | B73: Saraí Sánchez Mateo | C73: PV Consulta en línea | D73: 1800 | E73: TRANSFERENCIA
A74: 46153 | B74: Beatriz Melo | C74: Botox | D74: 5850 | E74: TARJETA DEBITO | F74: no
A75: 46153 | B75: Amanda Martínez Alanís | C75: subsecuente | D75: 1800 | E75: TARJETA CREDITO | F75: no
A76: 46153 | B76: Amanda Martínez Alanís | C76: ANTIBIOTIC | D76: 500 | E76: TARJETA CREDITO | F76: no
A77: 46153 | B77: Andrés Gregorio Uzcategui Gómez | C77: subsecuente | D77: 1800 | E77: TARJETA CREDITO | F77: si
A78: 46153 | B78: Andrés Gregorio Uzcategui Gómez | C78: minoxidil | D78: 2500 | E78: TARJETA CREDITO | F78: si
A79: 46153 | B79: Nicole Antonovich Taunton | C79: subsecuente | D79: 1800 | E79: TARJETA CREDITO | F79: no
A80: 46154 | B80: Jocelyn Gutierrez Nájera | C80: subsecuente | D80: 0 | E80: CORTESÍA
A81: 46154 | B81: Lua Hernández Lopez | C81: PV | D81: 1800 | E81: TARJETA DEBITO | F81: si
A82: 46154 | B82: Gabriela Sosa Miranda | C82: PV | D82: 1800 | E82: TARJETA DEBITO | F82: SI
A83: 46154 | B83: Pamela Guerrero Pérez | C83: subsecuente | D83: 1800 | E83: TARJETA CREDITO | F83: si
A84: 46154 | B84: Jocelyn Elizabeth Sierres Castillo | C84: PV | D84: 1800 | E84: TARJETA CREDITO | F84: si
A85: 46154 | B85: Jocelyn Elizabeth Sierres Castillo | C85: vastionin | D85: 1000 | E85: TARJETA CREDITO | F85: si
A86: 46154 | B86: Gustavo Ramírez de León | C86: BOTOX | D86: 5850 | E86: TARJETA CREDITO | F86: si
A87: 46154 | B87: Gustavo Ramírez de León | C87: MINIXIDIL | D87: 2500 | E87: TARJETA CREDITO | F87: si
A88: 46154 | B88: Jose Senado | C88: retoque | D88: 0 | E88: CORTESÍA
A89: 46154 | B89: Eugenio Villareal viera | C89: retoque | D89: 0 | E89: CORTESÍA
A90: 46154 | B90: Daniela Serrano Hamparzumian | C90: retoque | D90: 0 | E90: CORTESÍA
A91: 46155 | B91: Nelly Abarca | C91: subsecuente | D91: 1800 | E91: EFECTIVO | F91: no
A92: 46155 | B92: Nelly Abarca | C92: AG | D92: 500 | E92: EFECTIVO | F92: no
A93: 46155 | B93: Lorena Olvera Trejo | C93: subsecuente | D93: 1800 | E93: TARJETA CREDITO | F93: si
A94: 46155 | B94: Ines Martin Del Campo Rota | C94: subsecuente | D94: 1800 | E94: AMEX | F94: no
A95: 46155 | B95: Josep Nousairi Shacalo | C95: subsecuente | D95: 1800 | E95: EFECTIVO | F95: no
A96: 46155 | B96: Paola Pimentel Colin | C96: PV | D96: 1800 | E96: TARJETA CREDITO | F96: no
A97: 46155 | B97: Paola Pimentel Colin | C97: Loción | D97: 500 | E97: TARJETA CREDITO | F97: no
A98: 46155 | B98: Gabriela Noemi Molares | C98: botox | D98: 6500 | E98: TARJETA CREDITO | F98: no
A99: 46155 | B99: Gabriela Noemi Molares | C99: contorno de ojos | D99: 400 | E99: TARJETA CREDITO | F99: no
A100: 46155 | B100: Diana Menendez Preciat | C100: botox | D100: 5850 | E100: EFECTIVO | F100: no
A101: 46157 | B101: Maria Eugenia Ballestero Cameroni | C101: subsecuente | D101: 0 | E101: CORTESÍA
A102: 46157 | B102: Maria Soledad Garcia Moreno | C102: Sculptra | D102: 13000 | E102: TARJETA CREDITO | F102: no
A103: 46157 | B103: Eduardo Rios Vivero | C103: subsecuente | D103: 1800 | E103: TARJETA DEBITO | F103: no
A104: 46157 | B104: Lola Rivas Ordorica | C104: PV | D104: 1800 | E104: TARJETA CREDITO | F104: no
A105: 46157 | B105: Guadalupe Espinoza Vargas | C105: PV | D105: 1800 | E105: TARJETA CREDITO | F105: si
...

Sheet DR. CARLOS
A7: DR. CARLOS BARRERA
A8: FECHA | B8: NOMBRE DEL PACIENTE | C8: TIPO DE CONSULTA | D8: MONTO | E8: MEDIO DE PAGO | F8: FACTURADO | G8: NÚMERO RECIBO | H8: NÚMERO FACTURA | I8: FUENTE | J8: OBSERVACIONES
A9: 46144 | B9: Jorge Eduardo Rodríguez Loera | C9: retoque | D9: 0 | E9: CORTESÍA | F9: no
A10: 46144 | B10: Jorge Rodolfo Escamilla Torres | C10: Botox | D10: 6500 | E10: TARJETA CREDITO | F10: si | H10: A 9 | J10: Saldo a a favor $500
A11: 46144 | B11: Juan Carlos Guzman Solis | C11: procedimiento | D11: 2500 | E11: TARJETA DEBITO | F11: no
A12: 46144 | B12: Juan Carlos Guzman Solis | C12: 1 polaris + 3 minoxidil 5 | D12: 2800 | E12: TARJETA DEBITO | F12: no
A13: 46144 | B13: Jorge Gerardo Cruz Aguila | C13: inyecciones de dutasteride | D13: 2500 | E13: TARJETA CREDITO | F13: si | H13: A 10 | J13: envio CSF
A14: 46144 | B14: Paula Islas Cantu | C14: Subsecuente | D14: 1800 | E14: TARJETA CREDITO | F14: si | H14: A 14 | J14: factura solicitada
A15: 46144 | B15: Ana Guadalupe Gúzman Ariza | C15: luz pulsada | D15: 2500 | E15: TARJETA DEBITO | F15: NO
A16: 46144 | B16: Fabiola Flores Guadarrama | C16: PV | D16: 2000 | E16: TARJETA CREDITO | F16: no
A17: 46144 | B17: Fabiola Flores Guadarrama | C17: Mesoterapia | D17: 2500 | E17: TARJETA CREDITO | F17: no
A18: 46144 | B18: Fabiola Flores Guadarrama | C18: Polaris | D18: 1000 | E18: TARJETA CREDITO | F18: no
A19: 46144 | B19: María del Carmen Crespo Pozuelo | C19: PV | D19: 0 | E19: CORTESÍA
A20: 46146 | B20: Sharon Esquenazi Opatowski | C20: PV | D20: 2000 | E20: TARJETA CREDITO | F20: SI | H20: A 11 | J20: Factura soliicitada
A21: 46146 | B21: Claudia Perez Roldan | C21: sculptra | D21: 12500 | E21: TARJETA CREDITO | F21: SI | H21: A12 | J21: Factura soliicitada
A22: 46146 | B22: Tadeo Maximiliano Vargas Espinosa | C22: inyección de dutasteride | D22: 3000 | E22: TARJETA CREDITO | F22: Si | H22: PEND CSF | J22: Factura soliicitada
A23: 46146 | B23: Tadeo Maximiliano Vargas Espinosa | C23: 1 polaris + 4 minoxidil 5 | D23: 4900 | E23: TARJETA CREDITO | F23: si | J23: Factura soliicitada
A24: 46146 | B24: Alejandra Arocha Garreño | C24: Subsecuente | D24: 2000 | E24: TARJETA CREDITO | F24: NO
A25: 46146 | B25: Iñaki Alvarez Arocha | C25: PV | D25: 2000 | E25: TARJETA CREDITO | F25: NO
A26: 46147 | B26: Mauricio Alejandro Macias Ocaña | C26: 2 polaris | D26: 2000 | E26: TARJETA CREDITO | F26: si | H26: A13
A27: 46147 | B27: Valeria Garcia Herrerias | C27: PV | D27: 2000 | E27: TRANSFERENCIA | F27: si | H27: A 8
A28: 46147 | B28: Valeria Garcia Herrerias | C28: 3 minoxidil 1 mg | D28: 2800 | E28: TRANSFERENCIA | F28: si | H28: A 8
A29: 46147 | B29: Valeria Hernández Sánchez | C29: Subsecuente | D29: 0 | E29: CORTESÍA
A30: 46147 | B30: Alejandra Martinez Perez | C30: retoque | D30: 0
A31: 46147 | B31: Celia Masri Maya | C31: Subsecuente | D31: 1800 | E31: TARJETA CREDITO | F31: no
A32: 46147 | B32: Celia Masri Maya | C32: 1 epuris | D32: 1200 | E32: TARJETA CREDITO | F32: no | J32: saldo a favor $400
A33: 46147 | B33: Laura Poucel Maldonado | C33: PV | D33: 2000 | E33: TARJETA CREDITO | F33: si | H33: A 19
A34: 46147 | B34: Laura Poucel Maldonado | C34: 1 polaris + 1minoxidel 1mg | D34: 2100 | E34: TARJETA CREDITO | F34: si | H34: A 19
A35: 46147 | B35: Emiliano Cortina Saviñón | C35: PV | D35: 2000 | E35: TARJETA CREDITO | F35: no
A36: 46147 | B36: Luis Enrique Rodríguez Sánchez | C36: botox | D36: 6000 | E36: TARJETA CREDITO | F36: no
A37: 46147 | B37: Luis Enrique Rodríguez Sánchez | C37: profhilo | D37: 8000 | E37: TARJETA CREDITO | F37: no
A38: 46147 | B38: SOFIA AUXILIADORA RODRIGUEZ RODRIGUEZ | C38: profhilo | D38: 8000 | E38: TARJETA CREDITO | F38: no
A39: 46147 | B39: Begoña Elizalde | C39: PV | D39: 2000 | E39: EFECTIVO | F39: no
A40: 46147 | B40: Begoña Elizalde | C40: 1 minoxidil de 1mg | D40: 1100 | E40: EFECTIVO | F40: no
A41: 46147 | B41: Ángel Manuel García Ochoa | C41: Subsecuente | D41: 1800 | E41: TARJETA CREDITO | F41: no
A42: 46147 | B42: Ángel Manuel García Ochoa | C42: dutasteride | D42: 2500 | E42: TARJETA CREDITO | F42: no
A43: 46147 | B43: Ángel Manuel García Ochoa | C43: 3 polaris + 3 minoxidil de 5mg | D43: 5800 | E43: TARJETA CREDITO | F43: no
A44: 46147 | B44: Karla Melina Mendoza Rodriguez | C44: exosomas | D44: 4000 | E44: TARJETA CREDITO | F44: no
A45: 46147 | B45: Daniel Barrera Ochoa | C45: 2 minoxidil 5mg (90 caps) | D45: 0 | E45: CORTESÍA
A46: 46147 | B46: Gabriel Guaida | C46: 1 minoxidol 5m | D46: 1100 | E46: TARJETA CREDITO | F46: si | H46: A 7
A47: 46147 | B47: Ana Nicolas Cruz | C47: 1 epuris | D47: 0 | E47: CORTESÍA
A48: 46148 | B48: Hector Hugo Ceron Peralta | C48: 1 minoxidil 5mg +2 dutasteride +1 polaris | D48: 4100 | E48: TARJETA CREDITO | F48: no
A49: 46148 | B49: Daniela Feldman | C49: subsecuente | D49: 1700 | E49: EFECTIVO | F49: no
A50: 46148 | B50: Daniela Feldman | D50: 100 | E50: TARJETA DEBITO | F50: no
A51: 46148 | B51: José Ramón Gachúz Navarro | C51: inyección de dutasteride | D51: 3000 | E51: TARJETA CREDITO | F51: no
A52: 46148 | B52: José Ramón Gachúz Navarro | C52: 1 polaris | D52: 1000 | E52: TARJETA CREDITO | F52: no
A53: 46148 | B53: Natalia Arenas Ortiz | C53: retoque | D53: 0
A54: 46149 | B54: Mauricio Bierzwinsky | C54: Botox | D54: 6000 | E54: TRANSFERENCIA | F54: no | J54: cita 08/05/2026
A55: 46150 | B55: Leticia Gatica Mejia | C55: retoque /profhilo | D55: 8000 | E55: TARJETA CREDITO | F55: si | H55: A 26
A56: 46150 | B56: Pedro Alberto García Ramírez | C56: retoque /profhilo | D56: 8000 | E56: TARJETA CREDITO | F56: si | H56: A 26
A57: 46150 | B57: Leticia Gatica Mejia | C57: epuris | D57: 1600 | E57: TARJETA CREDITO | F57: si | H57: A 26
A58: 46150 | B58: Jessica Smeke Smeke | C58: PV/botox | D58: 1000 | E58: EFECTIVO | F58: no
A59: 46150 | B59: Mauricio Bierzwinsky | C59: PV/BOTOX | D59: 6000 | F59: no | J59: Se pago 07/05/2026
A60: 46150 | B60: Mauricio Bierzwinsky | C60: procedimiento quirurgico | D60: 1000 | E60: EFECTIVO | F60: no
A61: 46150 | B61: Mireya Yamile Morales Romo | C61: subsecuente/ peeling | D61: 3000 | E61: EFECTIVO | F61: no
A62: 46150 | B62: Marco Antonio Escalante López | C62: PV | D62: 2000 | E62: EFECTIVO | F62: no
A63: 46150 | B63: Luis Fernando Peña Peña | C63: profhilo | D63: 7500 | E63: TARJETA CREDITO | F63: si | H63: A16
A64: 46150 | B64: David Corona Balcazar | C64: subsecuente | D64: 4500 | E64: AMEX | F64: no
A65: 46150 | B65: Gerardo Noriega Zavala | C65: 3 minoxidil 2.5 + 2 dutasteride | D65: 4800 | E65: AMEX | F65: si | H65: A 22
A66: 46150 | B66: Diego Armas de la Vega | C66: 1 minoxidil 5mg | D66: 1100 | E66: TARJETA DEBITO | F66: si | H66: A 18
A67: 46150 | B67: Natalie Paola Marcushamer Gold | C67: 3minoxidil 1mg + 1 polaris | D67: 3800 | E67: TARJETA CREDITO | F67: no
A68: 46151 | B68: Rodrigo Ramirez De Riquer | C68: subsecuente/botox | D68: 6000 | E68: TARJETA CREDITO | F68: si | H68: PEND CSF
A69: 46151 | B69: Rodrigo Ramirez De Riquer | C69: 1 minoxidil 5 mg +1 dutasteride | D69: 2100 | E69: TARJETA CREDITO | F69: si
A70: 46151 | B70: Jessica Vanessa Barrera Martinez | C70: subsecuente/botox | D70: 6000 | E70: TARJETA CREDITO | F70: si | H70: A 17
A71: 46151 | B71: Jessica Vanessa Barrera Martinez | C71: 3 minoxidil 1 mg | D71: 2800 | E71: TARJETA CREDITO | F71: no
A72: 46151 | B72: Ana Victoria Wong De La Torre | C72: PV | D72: 2000 | E72: EFECTIVO | F72: no
A73: 46151 | B73: Begoña Bolaños Meade | C73: PV/botox | D73: 6000 | E73: TARJETA DEBITO | F73: no
A74: 46151 | B74: Aimee Calleja Aguilar | C74: subsecuente | D74: 1800 | E74: TARJETA CREDITO | F74: no
A75: 46151 | B75: Alejandra Alonso Asho | C75: retoque | D75: 0 | E75: CORTESÍA | F75: no
A76: 46151 | B76: Luis Lauro Moreno Ricard | C76: 1 minoxidil 5mg | D76: 1100 | E76: TARJETA DEBITO | F76: no
A77: 46151 | B77: Carlos Aparicio Garcia | C77: 1 minoxidil 5mg | D77: 1100 | E77: AMEX | F77: no
A78: 46153 | B78: Pamela Keller Bimstein | C78: PV | D78: 2000 | E78: TARJETA CREDITO | F78: NO
A79: 46153 | B79: Pamela Keller Bimstein | C79: 1 Minoxidil 1mg | D79: 1100 | E79: EFECTIVO | F79: NO
A80: 46153 | B80: Asenet Martinez Orozco | C80: CO2 | D80: 5000 | E80: AMEX | F80: no
A81: 46153 | B81: Esther Hernández Sánchez | D81: 2000 | E81: TARJETA CREDITO | F81: no
A82: 46153 | B82: Esther Hernández Sánchez | C82: 1 Minoxidil 1mg | D82: 1100 | E82: TARJETA CREDITO | F82: no
A83: 46154 | B83: Gabriela Castro Trigueros | C83: 1 minoxidil 2.5 mg +1 dutasteride | D83: 2100 | E83: TARJETA DEBITO | F83: no
A84: 46154 | B84: Gabriel Guaida | C84: 1 polaris | D84: 1000 | E84: TARJETA CREDITO | F84: si | H84: A 20
A85: 46154 | B85: Jenny Alexandra Urrego Rodriguez | C85: acido tranexamico | D85: 1000 | E85: TARJETA CREDITO | F85: si | H85: A 23
A86: 46154 | B86: Cristina Cabral Moreno | C86: subsecuente | D86: 1800 | E86: TARJETA CREDITO | F86: no
A87: 46154 | B87: Cristina Cabral Moreno | C87: 3 minoxidil 2.5 | D87: 2800 | E87: TARJETA CREDITO | F87: no
A88: 46154 | B88: Ramón Fernández Loperena | C88: Mesoterapia de dutasteride | D88: 3000 | E88: TARJETA CREDITO | F88: si | H88: A 25
A89: 46154 | B89: Ramón Fernández Loperena | C89: 3 minoxidil 5mg | D89: 2800 | E89: TARJETA CREDITO | F89: si | H89: A 25
A90: 46155 | B90: Noor Bechara Boulos | C90: subsecuente | D90: 1800 | E90: TARJETA CREDITO | F90: no
A91: 46155 | B91: Noor Bechara Boulos | C91: 1 epuris | D91: 1600 | E91: TARJETA CREDITO | F91: no
A92: 46155 | B92: Claudia Cristina Barrera Carmona | C92: subsecuente/profhilo | D92: 5000 | E92: TARJETA CREDITO | F92: no
A93: 46155 | B93: Paola Pimentel Colin | C93: PV | D93: 2000 | E93: TARJETA CREDITO | F93: no
A94: 46155 | B94: Paola Pimentel Colin | C94: 3 polaris + 3 minoxidil de 1mg | D94: 5800 | E94: TARJETA CREDITO | F94: no
A95: 46155 | B95: Jimena Garcia Reissenweber | C95: subsecuente | D95: 2500 | E95: EFECTIVO
A96: 46155 | B96: Gisela Ruiz De Chavez | C96: subsecuente | D96: 1800 | E96: TARJETA CREDITO | F96: no
A97: 46155 | B97: Gisela Ruiz De Chavez | C97: 1 polaris + 1 minoxidil 1mg | D97: 2100 | E97: TARJETA CREDITO | F97: no
A98: 46155 | B98: Sofia Cano Ruiz de Chávez | C98: subsecuente | D98: 1500 | E98: EFECTIVO | F98: no
A99: 46155 | B99: Sofia Cano Ruiz de Chávez | C99: PV | D99: 300 | E99: TARJETA CREDITO
A100: 46156 | B100: Maite Maria Dunand Raymond | C100: PV | D100: 2000 | E100: TARJETA DEBITO | F100: no
A101: 46156 | B101: Maite Maria Dunand Raymond | C101: capilarium capixy | D101: 1000 | E101: TARJETA DEBITO | F101: no
A102: 46156 | B102: Angel Antonio Garcia Cancino | C102: PV | D102: 1500 | E102: TARJETA DEBITO | F102: no
A103: 46156 | B103: Angel Antonio Garcia Cancino | D103: 500 | E103: EFECTIVO | F103: no
A104: 46156 | B104: Adriana Álvarez Martínez | C104: PV | D104: 2000 | E104: TARJETA CREDITO | F104: si | J104: pend. CSF
A105: 46156 | B105: Adriana Álvarez Martínez | C105: 1 polaris+3 minoxidil 1mg | D105: 3800 | E105: TARJETA CREDITO | F105: si
A106: 46156 | B106: Patricia Isabel Iglesias Martinez | C106: PV/procedimiento | D106: 2000 | E106: TARJETA CREDITO | F106: no
...

Sheet COSM. KARELY
A7: KARELY
A8: FECHA | B8: NOMBRE DEL PACIENTE | C8: TIPO DE CONSULTA | D8: MONTO | E8: MEDIO DE PAGO | F8: FACTURADO | G8: NÚMERO RECIBO | H8: NÚMERO FACTURA | I8: FUENTE | J8: OBSERVACIONES
A9: 46144 | B9: Eduardo Rios Vivero | C9: limpieza facial | D9: 1200 | E9: TARJETA CREDITO | F9: no | J9: cobro dr, Carlos
A10: 46144 | B10: Mariam Gutierrez | C10: dermapen | D10: 3500 | E10: TARJETA CREDITO | F10: no | J10: cobro dra. Ale
A11: 46148 | B11: Natalia Arenas Ortiz | C11: geneo | D11: 2000 | E11: TARJETA CREDITO | F11: no | J11: cobro dr, Carlos
A12: 46149 | B12: Emilia Schvartzman Berman | C12: Hydrafacial | D12: 2125 | E12: AMEX | F12: si | H12: A 15 | J12: cobro dr, Carlos
A13: 46150 | B13: Jesica Smeke Smeke | C13: Luz pulsada | D13: 2000 | E13: TARJETA CREDITO | F13: no | J13: cobro dr, Carlos
A14: 46150 | B14: Mireya Yamile Morales Romo | C14: Hydrafacial | D14: 2720 | E14: EFECTIVO | F14: no
A15: 46150 | B15: Camila Soto | C15: Hydrafacial deluxe | D15: 2720
A16: 46154 | B16: Pamela Guerrero Pérez | C16: Hydrafacial deluxe | D16: 2720 | E16: TARJETA CREDITO | F16: SI | J16: cobro dra. Ale
A17: 46155 | B17: Jazmin Lozano | C17: depilación | D17: 0 | E17: CORTESÍA | J17: 5/de 5 consultas
A18: 46156 | B18: Fabiola Flores Guadarrama | C18: geneo | D18: 2000 | E18: TARJETA CREDITO | F18: no
A19: 46157 | B19: Jack Romano Grimberg | C19: limpieza facial | D19: 1200 | E19: TARJETA CREDITO
A20: 46158 | B20: Juan Alberto Becerra Martínez | C20: Laser M22 | D20: 3500 | E20: TARJETA DEBITO | J20: cobro dra. Ale
A21: 46158 | B21: Alicia Luna Zarate | C21: Hydrafacial deluxe | D21: 2720 | E21: TARJETA CREDITO | J21: cobro dr, Carlos
A22: 46160 | B22: Lucia Escalante Barbabosa | C22: Luz pulsada | D22: 3000 | E22: TARJETA CREDITO | J22: cobro dra. Ale
A23: 46162 | B23: Marcos Rivera Hernandez | C23: depilación laser media cara | D23: 700 | E23: TARJETA DEBITO | J23: cobro dra. Ale
A24: 46164 | B24: Gabriela Buenfil
A25: 46164 | B25: David Corona Balcazar | C25: Hydrafacial signature | D25: 2500 | E25: TARJETA CREDITO
A26: 46168 | B26: Víctor Eduardo Mejia Gonzalez | C26: facial | D26: 1200 | E26: TARJETA CREDITO | J26: cobro dr, Carlos
A27: 46168 | B27: Mariano Alberto Mazariegos Robles | C27: tricopat | D27: 3500 | E27: TARJETA CREDITO | F27: si
A28: 46169 | B28: José David González Romero | C28: tricopat | D28: 3500 | E28: TARJETA CREDITO | F28: no
A29: 46169 | B29: Irene Ambe Sitton | C29: Hydrafacial signature | D29: 2000 | E29: EFECTIVO
A30: 46169 | B30: Irene Ambe Sitton | C30: Hydrafacial signature | D30: 125 | E30: tarjeta
A31: 46170 | B31: Mariana Alcala Robles | C31: CO2 | D31: 2900 | E31: EFECTIVO | F31: no
A32: 46170 | B32: Mariana Alcala Robles | D32: 1600 | E32: TARJETA CREDITO | F32: no
A33: 46170 | B33: Maria Guadalupe Trejo Rodríguez | D33: 3500 | E33: TARJETA CREDITO | F33: si
A34: 46171 | B34: Anais Atilano Velásquez | C34: tricopat | D34: 3500 | E34: TARJETA DEBITO | F34: si

Sheet COSMETOLOGA KARLA.  
A7: Karla
A8: FECHA | B8: NOMBRE DEL PACIENTE | C8: TIPO DE CONSULTA | D8: MONTO | E8: MEDIO DE PAGO | F8: FACTURADO | G8: NÚMERO RECIBO | H8: NÚMERO FACTURA | I8: FUENTE | J8: OBSERVACIONES
A9: 46146 | B9: Miguel Angel Zavala Moreno | C9: Hydrafacial DELUXE | D9: 2720 | E9: AMEX | F9: no | J9: se cobro dr. Carlos
A10: 46146 | B10: Mariana Lopez Anaya | C10: depilacion | D10: 4300 | E10: TARJETA CREDITO | F10: no | J10: se cobro dr. Carlos
A11: 46146 | B11: Luciana Pandal López | C11: depilacion piernas | D11: 1800 | E11: TARJETA CREDITO | F11: no | J11: se cobro dr. Carlos
A12: 46146 | B12: Luciana Pandal López | C12: depilacion bigote | D12: 500 | E12: TARJETA CREDITO | F12: no | J12: se cobro dr. Carlos
A13: 46146 | B13: Karlo Imanuel Galindo Ramírez | C13: limpeza facial | D13: 1200 | E13: TARJETA CREDITO | J13: se cobro dra. Ale
A14: 46147 | B14: Alejandra Martinez Perez | C14: Limpieza e hidratación | D14: 1500 | E14: TARJETA CREDITO | F14: no
A15: 46147 | B15: Lucia Escalante Barbabosa | C15: depilación media cara | D15: 700 | E15: TARJETA CREDITO | F15: no | J15: se cobro dra. Ale
A16: 46147 | B16: Valeria Hernández Sánchez | C16: Hydrafacial DELUXE | D16: 2560 | E16: EFECTIVO | F16: no | J16: caja 2500
A17: 46148 | B17: Maria Isabel Alatorre | C17: limpieza | D17: 1000 | E17: EFECTIVO | F17: no | J17: caja
A18: 46148 | D18: 200 | E18: TARJETA CREDITO | F18: no | J18: se cobro dr.Carlos
A19: 46149 | B19: Marina Cortes García | C19: Depilación cara completa | D19: 1100 | E19: AMEX | F19: no
A20: 46149 | B20: Paola Huelga Correa | C20: limpieza | D20: 1200 | E20: AMEX | F20: no | J20: se cobro dr.Carlos
A21: 46150 | B21: Ander Ovejas | C21: Depilación láser | D21: 1700 | E21: EFECTIVO | F21: no | J21: caja
A22: 46150 | B22: Clara Torres | C22: GENEO | D22: 2000 | E22: AMEX | F22: si
A23: 46150 | B23: Maria Rivero Borrell | C23: limpieza Facial | D23: 1200 | E23: TARJETA CREDITO | F23: no | J23: se cobro dr.Carlos
A24: 46150 | B24: Daphne Yamileth Ugalde Peña | C24: limpieza facial | D24: 1200 | E24: TARJETA DEBITO | F24: no | J24: se cobro dra. Ale
A25: 46150 | B25: Daphne Yamileth Ugalde Peña | C25: Limpieza de espalda | D25: 1200 | E25: TARJETA DEBITO | F25: no | J25: se cobro dra. Ale
A26: 46150 | B26: Abigail Paniagua Vizcarra | C26: Luz pulsada | D26: 3500 | E26: TARJETA CREDITO | F26: no | J26: se cobro dra. Ale
A27: 46151 | B27: Luciano Perez Alonso | C27: facial | D27: 1200 | E27: TARJETA CREDITO | F27: no | J27: se cobro dr.Carlos
A28: 46151 | B28: Alejandra Garcia Vizcaino | C28: Hydrafacial DELUXE | D28: 2720 | E28: TARJETA CREDITO | F28: si | J28: se cobro dr.Carlos
A29: 46151 | B29: Andrea Fornelli | C29: limpeza facial | D29: 1500 | E29: TARJETA CREDITO | F29: no | J29: se cobro dr.Carlos
A30: 46153 | B30: Jannet Martínez Villegas | C30: Luz pulsada | D30: 0 | E30: CORTESÍA | F30: no | J30: pagada 22/04/2026
A31: 46153 | B31: Nicole Antonovich Taunton | C31: limpieza | D31: 1200 | E31: TARJETA CREDITO | F31: no | J31: se cobro dra. Ale
A32: 46154 | B32: Cecilia Marcela Ramírez Suttclife | C32: co2 | D32: 5000 | E32: EFECTIVO | F32: no | J32: Se entrega Efec a la DRA.
A33: 46154 | B33: Cecilia Marcela Ramírez Suttclife | C33: Luz pulsada | D33: 5000 | E33: EFECTIVO | F33: no | J33: Se entrega Efec a la DRA.
A34: 46154 | B34: Jose Senado | C34: Hydrafacial DELUXE | D34: 2720 | E34: TARJETA CREDITO | F34: si | J34: se cobro dra. Ale
... A38: 46155 | B38: Claudia Cristina Barrera Carmona | C38: Depilación de cara completa y axilas | D38: 1950 | E38: TARJETA CREDITO | F38: no | J38: se cobro dr.Carlos
A39: 46157 | B39: Zeltzin Rosas Espinoza | C39: Hydrafacial DELUXE | D39: 2720 | E39: EFECTIVO | F39: NO
A40: 46160 | B40: Paula Andrea Fabrega Roncagliolo | C40: Hydrafacial DELUXE | D40: 3400 | E40: TRANSFERENCIA | F40: no
A41: 46161 | B41: Lizbeth Meléndez Hernández | C41: dermapen | D41: 3500 | E41: TARJETA CREDITO | F41: SI | J41: se cobro dr. Carlos
A42: 46161 | B42: Ledicia Benabou Benmaman | C42: facial
A43: 46162 | B43: Amanda Martínez Alanís | C43: limpieza | D43: 1200 | E43: TARJETA CREDITO | F43: no
A44: 46162 | B44: Elia Annette Bernard Guerrero | C44: geneo | D44: 2000 | E44: TARJETA CREDITO | F44: no
A45: 46162 | B45: Silvana Ramirez Angulo | C45: limpieza | D45: 1000 | E45: TARJETA CREDITO | J45: se cobro dra. Ale
A46: 46162 | B46: Silvana Ramirez Angulo | D46: 200 | E46: EFECTIVO
A47: 46163 | B47: Claudia Cristina Barrera Carmona | C47: Hydrafacial DELUXE | D47: 2720 | E47: TARJETA CREDITO | F47: no | J47: se cobro dr Carlos
A48: 46163 | B48: Fernanda Arroyo Aldana | C48: Hydrafacial DELUXE | D48: 2720 | E48: TARJETA CREDITO | F48: no | J48: se cobro dr Carlos
A49: 46164 | B49: Kelin Areli Olvera Quiroz | C49: limpieza facial profunda | D49: 1200 | E49: EFECTIVO | F49: no | J49: caja
A50: 46164 | B50: Paulina Lujambio Mondragon | C50: hydrafacial deluxe | D50: 2720 | E50: AMEX | F50: no | J50: se cobro dr Carlos
A51: 46164 | B51: Alejandra Martinez Perez | C51: Hydrafacial Platinum | D51: 3400 | E51: TARJETA CREDITO | F51: no | J51: se cobro dr Carlos
A52: 46164 | B52: Mireille Donaji Arango Mathieu | C52: lasser axila | D52: 850 | E52: TARJETA CREDITO | F52: no | J52: se cobro dra. Ale
A53: 46164 | B53: Brenda Villanueva | C53: Limpieza con Hidratación | D53: 1500 | E53: TARJETA CREDITO | F53: no | J53: se cobro dra. Ale
A54: 46164 | B54: Mía Levinstein Morales | C54: bigote | D54: 850 | E54: TARJETA CREDITO | F54: si | J54: se cobro dra. Ale
A55: 46164 | B55: Mía Levinstein Morales | C55: axilas | D55: 800 | E55: TARJETA CREDITO | F55: si | J55: se cobro dra. Ale
A56: 46165 | B56: Rodrigo Ramirez De Riquer | C56: Hydrafacial signature | D56: 2500 | E56: TARJETA CREDITO | F56: no | J56: se cobro dr Carlos
A57: 46168 | B57: Jhon Baudovin | C57: Luz pulsada | D57: 3200 | E57: AMEX | F57: no | J57: se cobro dr Carlos
A58: 46168 | B58: Orlando Gutierrez Aragon | C58: tricopat | D58: 3500 | E58: TARJETA CREDITO | J58: se cobro dr Carlos
A59: 46168 | B59: Nathali Rodriguez Avila | C59: tricopat | D59: 3500 | E59: TARJETA CREDITO | J59: se cobro dr Carlos
A60: 46169 | B60: Maria Jose Farias Hernandez | C60: limpieza | D60: 1200 | E60: TARJETA CREDITO | F60: si | G60: pend factura | J60: se cobro dr Carlos
A61: 46169 | B61: Macarena Alatorre | C61: limpieza | D61: 1200 | E61: TARJETA CREDITO | F61: no | J61: se cobro dr Carlos
A62: 46170 | B62: Lucia Ogarrio | C62: dermapen | D62: 4500 | E62: TARJETA DEBITO | F62: no | J62: se cobro dr Carlos
A63: 46170 | B63: Renata González Martínez | C63: facial | D63: 1500 | E63: TARJETA CREDITO | J63: se cobro dr Carlos
A64: 46171 | B64: Macarena Alatorre | D64: 0 | E64: CORTESÍA
A65: 46171 | B65: Silvana Dávila Primmer | C65: limpieza facial | D65: 1200 | E65: TARJETA CREDITO | F65: no | J65: se cobro dr Carlos
A66: 46171 | B66: Deneb Algedi Morales Barquet | C66: depilación | D66: 2800 | E66: TARJETA CREDITO | F66: no | J66: se cobro dr Carlos
A67: 46171 | B67: Mía Levinstein Morales | C67: medias Piernas | D67: 1100 | E67: TARJETA CREDITO | F67: no | J67: se cobro dr Carlos

Sheet CIERRE DIARIO
A7: FECHA
A8: 46176
A10: EQUIPO | B10: AMEX | C10: EFECTIVO | D10: TARJETA CREDITO | E10: TARJETA DEBITO | F10: TRANSFERENCIA | G10: TOTAL
A11: DRA. ALEJANDRA GUERRERO | B11: =+SUMIFS(BD_ALEJANDRA[MONTO],BD_ALEJANDRA[MEDIO DE PAGO],'CIERRE DIARIO'!$B$10,BD_ALEJANDRA[FECHA],'CIERRE DIARIO'!$A$8) -> 0 | C11: =+SUMIFS(BD_ALEJANDRA[MONTO],BD_ALEJANDRA[MEDIO DE PAGO],$C$10,BD_ALEJANDRA[FECHA],'CIERRE DIARIO'!$A$8) -> 0 | D11: =+SUMIFS(BD_ALEJANDRA[MONTO],BD_ALEJANDRA[MEDIO DE PAGO],$D$10,BD_ALEJANDRA[FECHA],'CIERRE DIARIO'!$A$8) -> 0 | E11: =+SUMIFS(BD_ALEJANDRA[[#All],[MONTO]],BD_ALEJANDRA[[#All],[MEDIO DE PAGO]],'CIERRE DIARIO'!$E$10,BD_ALEJANDRA[[#All],[FECHA]],'CIERRE DIARIO'!$A$8) -> 0 | F11: =+SUMIFS(BD_ALEJANDRA[[#All],[MONTO]],BD_ALEJANDRA[[#All],[MEDIO DE PAGO]],$F$10,BD_ALEJANDRA[[#All],[FECHA]],'CIERRE DIARIO'!$A$8) -> 0 | G11: =+SUM(B11:F11) -> 0
A12: DR. CARLOS BARRERA | B12: =+SUMIFS(BD_CARLOS[MONTO],BD_CARLOS[MEDIO DE PAGO],'CIERRE DIARIO'!$B$10,BD_CARLOS[FECHA],'CIERRE DIARIO'!$A$8) -> 0 | C12: =+SUMIFS(BD_CARLOS[MONTO],BD_CARLOS[MEDIO DE PAGO],$C$10,BD_CARLOS[FECHA],'CIERRE DIARIO'!$A$8) -> 0 | D12: =+SUMIFS(BD_CARLOS[MONTO],BD_CARLOS[MEDIO DE PAGO],$D$10,BD_CARLOS[FECHA],'CIERRE DIARIO'!$A$8) -> 0 | E12: =+SUMIFS(BD_CARLOS[[#All],[MONTO]],BD_CARLOS[[#All],[MEDIO DE PAGO]],'CIERRE DIARIO'!$E$10,BD_CARLOS[[#All],[FECHA]],'CIERRE DIARIO'!$A$8) -> 0 | F12: =+SUMIFS(BD_CARLOS[[#All],[MONTO]],BD_CARLOS[[#All],[MEDIO DE PAGO]],$F$10,BD_CARLOS[[#All],[FECHA]],'CIERRE DIARIO'!$A$8) -> 0 | G12: =+SUM(B12:F12) -> 0
A13: COSM. KARELY MONTES | B13: =+SUMIFS(BD_COSM1[MONTO],BD_COSM1[MEDIO DE PAGO],'CIERRE DIARIO'!$B$10,BD_COSM1[FECHA],'CIERRE DIARIO'!$A$8) -> 0 | C13: =+SUMIFS(BD_COSM1[MONTO],BD_COSM1[MEDIO DE PAGO],$C$10,BD_COSM1[FECHA],'CIERRE DIARIO'!$A$8) -> 0 | D13: =+SUMIFS(BD_COSM1[MONTO],BD_COSM1[MEDIO DE PAGO],$D$10,BD_COSM1[FECHA],'CIERRE DIARIO'!$A$8) -> 0 | E13: =+SUMIFS(BD_COSM1[[#All],[MONTO]],BD_COSM1[[#All],[MEDIO DE PAGO]],'CIERRE DIARIO'!$E$10,BD_COSM1[[#All],[FECHA]],'CIERRE DIARIO'!$A$8) -> 0 | F13: =+SUMIFS(BD_COSM1[[#All],[MONTO]],BD_COSM1[[#All],[MEDIO DE PAGO]],$F$10,BD_COSM1[[#All],[FECHA]],'CIERRE DIARIO'!$A$8) -> 0 | G13: =+SUM(B13:F13) -> 0
A14: COSM. KARLA | B14: =+SUMIFS(BD_COSM2[MONTO],BD_COSM2[MEDIO DE PAGO],'CIERRE DIARIO'!$B$10,BD_COSM2[FECHA],'CIERRE DIARIO'!$A$8) -> 0 | C14: =+SUMIFS(BD_COSM2[MONTO],BD_COSM2[MEDIO DE PAGO],$C$10,BD_COSM2[FECHA],'CIERRE DIARIO'!$A$8) -> 0 | D14: =+SUMIFS(BD_COSM2[MONTO],BD_COSM2[MEDIO DE PAGO],$D$10,BD_COSM2[FECHA],'CIERRE DIARIO'!$A$8) -> 0 | E14: =+SUMIFS(BD_COSM2[[#All],[MONTO]],BD_COSM2[[#All],[MEDIO DE PAGO]],'CIERRE DIARIO'!$E$10,BD_COSM2[[#All],[FECHA]],'CIERRE DIARIO'!$A$8) -> 0 | F14: =+SUMIFS(BD_COSM2[[#All],[MONTO]],BD_COSM2[[#All],[MEDIO DE PAGO]],$F$10,BD_COSM2[[#All],[FECHA]],'CIERRE DIARIO'!$A$8) -> 0 | G14: =+SUM(B14:F14) -> 0
A16: TOTAL | B16: =+SUM(B11:B14) -> 0 | C16: =+SUM(C11:C14) -> 0 | D16: =+SUM(D11:D14) -> 0 | E16: =+SUM(E11:E14) -> 0 | F16: =+SUM(F11:F14) -> 0 | G16: =+SUM(G11:G14) -> 0

Sheet INVENTARIO
A1: {=A1:Q38} -> 0 | E1: INVENTARIO DE MEDICAMENTOS DR. BARRERA
A3: PRODUCTO | B3: FECHA
B4: 46174
A5: Minoxidil 2.5 mg | B5: 24
A6: Minoxidil 5 mg | B6: 18
A7: Minoxidil 5 mg c/90 tab | B7: 7
A8: Minoxidil 1 mg | B8: 18
A9: Polaris | B9: 15
A10: Folcare | B10: 0
A11: Capilarium CAPIXYL | B11: 5
A12: Capilarium MINOXIDIL | B12: 9
A13: Dutasteride | B13: 22
A14: Epuris | B14: 17
A15: Acido Trexamico | B15: 0
A16: Nourkrim | B16: 0
... A20: Gel sebiaclear | B20: 5
A22: PRODUCTO | B22: FECHA | C22: INGRESOS | D22: FECHA | E22: INGRESOS | F22: INGRESOS | G22: FECHA | H22: FECHA | I22: FECHA | J22: INGRESOS | K22: INGRESOS | L22: FECHA | M22: INGRESOS | N22: INGRESOS | O22: FECHA | P22: INGRESOS | Q22: fecha
A23: Minoxidil 2.5 mg
A24: Minoxidil 5 mg
A25: Minoxidil 5 mg c/90 tab
A26: Minoxidil 1 mg
A27: Polaris
A28: Folcare
A29: Capilarium CAPIXYL
A30: Capilarium MINOXIDIL
A31: Dutasteride
A32: Epuris
A33: Acido Trexamico
A34: Nourkrim
... A38: Gel sebiaclear
A39: PRODUCTO | B39: FECHA | C39: INGRESOS | D39: FECHA | E39: INGRESOS | F39: INGRESOS | G39: FECHA | H39: FECHA | I39: FECHA | J39: INGRESOS | K39: INGRESOS | L39: FECHA | M39: INGRESOS | N39: INGRESOS | O39: FECHA | P39: INGRESOS | Q39: fecha
B40: 46118 | D40: 46125 | E40: 46125 | F40: 46127 | G40: 46132 | H40: 46140 | I40: 46147 | J40: 46149 | K40: 46154 | L40: 46156 | M40: 46156 | N40: 46157 | O40: 46160 | P40: 46170 | Q40: 46167
A41: Minoxidil 2.5 mg | B41: 3 | D41: 19 | F41: 20 | G41: 38 | H41: 31 | I41: 30 | L41: 22 | O41: 19 | P41: 25 | Q41: 12
A42: Minoxidil 5 mg | B42: 25 | D42: 40 | F42: 40 | G42: 72 | H42: 66 | I42: 54 | L42: 42 | O42: 37 | Q42: 31
A43: Minoxidil 5 mg c/90 tab | B43: 10 | D43: 9 | G43: 9 | H43: 9 | I43: 9 | L43: 7 | O43: 7 | Q43: 7
A44: Minoxidil 1 mg | B44: 28 | D44: 1 | F44: 40 | G44: 37 | H44: 30 | I44: 25 | L44: 8 | N44: 30 | O44: 31 | Q44: 28
A45: Polaris | B45: 20 | D45: 0 | E45: 40 | G45: 36 | H45: 25 | I45: 13 | J45: 40 | L45: 42 | O45: 29 | Q45: 23
A46: Folcare | B46: 0 | D46: 0 | G46: 0 | H46: 0 | I46: 0 | L46: 0 | O46: 0 | Q46: 0
A47: Capilarium CAPIXYL | B47: 0 | D47: 0 | G47: 0 | H47: 0 | I47: 0 | K47: 20 | L47: 10 | O47: 9 | Q47: 8
A48: Capilarium MINOXIDIL | M48: 20 | O48: 15 | Q48: 12
A49: Dutasteride | B49: 13 | D49: 9 | F49: 20 | G49: 26 | H49: 25 | I49: 21 | L49: 15 | O49: 5 | P49: 20 | Q49: 4
A50: Epuris | B50: 47 | D50: 39 | G50: 37 | H50: 36 | I50: 33 | L50: 29 | O50: 29 | Q50: 19
A51: Acido Trexamico | B51: 3 | D51: 2 | G51: 2 | H51: 2 | I51: 2 | L51: 0 | O51: 0 | Q51: 0
A52: Nourkrim | B52: 1 | D52: 0 | G52: 0 | H52: 0 | I52: 0 | L52: 0 | O52: 0 | Q52: 0
A53: Dermazone | B53: 8 | D53: 8 | G53: 8 | H53: 8 | I53: 8 | L53: 8 | O53: 8 | Q53: 8
A54: Gel hydra essence | Q54: 5
A55: Lazartigue | Q55: 5
A56: Gel sebiaclear | Q56: 5

Sheet Listas
A1: DOCTOR | B1: TIPO CONSULTA | C1: MEDIOS DE PAGO | D1: FUENTE
A2: DRA. ALEJANDRA GUERRERO | B2: PRIMERA VEZ | C2: AMEX | D2: DOCTORALIA
A3: DR. CARLOS BARRERA | B3: SUBSECUENTE | C3: CORTESÍA | D3: GOOGLE
A4: COSM. KARELY MONTES | C4: EFECTIVO | D4: RECOMENDACIÓN
C5: PAGADO | D5: RRSS
C6: TARJETA CREDITO
C7: TARJETA DEBITO
C8: TRANSFERENCIA
